haproxy_fusion/__init__.py
haproxy_fusion/haproxy_fusion_service.py
haproxy_fusion/api/haproxy_fusion_api_client.py
haproxy_fusion/models/base/base_model.py
haproxy_fusion/models/cluster/addon.py
haproxy_fusion/models/cluster/cluster.py
haproxy_fusion/models/cluster/label.py
haproxy_fusion/models/cluster/resources_version.py
haproxy_fusion/models/cluster_configuration/cluster_configuration.py
haproxy_fusion/models/cluster_configuration/backend/backend.py
haproxy_fusion/models/cluster_configuration/backend/balance.py
haproxy_fusion/models/cluster_configuration/backend/enums/adv_check.py
haproxy_fusion/models/cluster_configuration/backend/enums/balance_algorithm.py
haproxy_fusion/models/cluster_configuration/backend/enums/http_connection_mode.py
haproxy_fusion/models/cluster_configuration/backend/enums/http_restrict_req_hdr_names.py
haproxy_fusion/models/cluster_configuration/backend/enums/http_reuse.py
haproxy_fusion/models/cluster_configuration/backend/enums/load_server_state_from_file.py
haproxy_fusion/models/cluster_configuration/backend/enums/mode.py
haproxy_fusion/models/cluster_configuration/enums/enabled_disabled.py
haproxy_fusion/models/cluster_configuration/global_configuration/cpu_map.py
haproxy_fusion/models/cluster_configuration/global_configuration/default_path.py
haproxy_fusion/models/cluster_configuration/global_configuration/device_atlas_options.py
haproxy_fusion/models/cluster_configuration/global_configuration/fifty_one_degrees_options.py
haproxy_fusion/models/cluster_configuration/global_configuration/global_configuration.py
haproxy_fusion/models/cluster_configuration/global_configuration/h1_case_adjust_item.py
haproxy_fusion/models/cluster_configuration/global_configuration/log_send_hostname.py
haproxy_fusion/models/cluster_configuration/global_configuration/log_target.py
haproxy_fusion/models/cluster_configuration/global_configuration/lua_load.py
haproxy_fusion/models/cluster_configuration/global_configuration/lua_prepend_path.py
haproxy_fusion_client-0.1.1.dist-info/licenses/LICENSE
haproxy_fusion_client-0.1.1.dist-info/METADATA
haproxy_fusion_client-0.1.1.dist-info/WHEEL
haproxy_fusion_client-0.1.1.dist-info/top_level.txt
haproxy_fusion_client-0.1.1.dist-info/RECORD
