Metadata-Version: 2.4
Name: haproxy-fusion-client
Version: 0.1.1
Summary: A client and service wrapper for HAProxy Fusion API
Author-email: Henry Pikner <henrypikner@gmail.com>
License: MIT
Project-URL: Homepage, https://github.com/hepikn/haproxy-fusion-client
Requires-Python: >=3.12
License-File: LICENSE
Requires-Dist: dnspython>=2.7.0
Requires-Dist: pydantic>=2.11.1
Requires-Dist: requests>=2.32.3
Dynamic: license-file
